antelope/__init__.py
antelope/exchanges_from_spreadsheet.py
antelope/xdb_tokens.py
antelope/flows/__init__.py
antelope/flows/flow.py
antelope/flows/flow_interface.py
antelope/flows/openlca_locales.json
antelope/interfaces/__init__.py
antelope/interfaces/abstract_query.py
antelope/interfaces/ibackground.py
antelope/interfaces/ibasic.py
antelope/interfaces/iconfigure.py
antelope/interfaces/iexchange.py
antelope/interfaces/iforeground.py
antelope/interfaces/iindex.py
antelope/interfaces/iquantity.py
antelope/models/__init__.py
antelope/models/auth.py
antelope/models/comparators.py
antelope/qdb/__init__.py
antelope/qdb/qdb.py
antelope/qdb/units.py
antelope/refs/__init__.py
antelope/refs/base.py
antelope/refs/catalog_ref.py
antelope/refs/exchange_ref.py
antelope/refs/flow_ref.py
antelope/refs/process_ref.py
antelope/refs/quantity_ref.py
antelope/refs/tests/__init__.py
antelope/refs/tests/test_flows.py
antelope_interface-0.3.3.1.dist-info/licenses/LICENSE
antelope_interface-0.3.3.1.dist-info/METADATA
antelope_interface-0.3.3.1.dist-info/WHEEL
antelope_interface-0.3.3.1.dist-info/top_level.txt
antelope_interface-0.3.3.1.dist-info/RECORD
