Metadata-Version: 2.4
Name: antelope_interface
Version: 0.3.3.1
Summary: A common interface for accessing LCA data
Author-email: Brandon Kuczenski <bkuczenski@ucsb.edu>
License: BSD-3-Clause
Keywords: one,two
Classifier: Development Status :: 4 - Beta
Classifier: Intended Audience :: Science/Research
Classifier: License :: OSI Approved :: BSD License
Classifier: Natural Language :: English
Classifier: Operating System :: OS Independent
Classifier: Programming Language :: Python :: 3
Classifier: Topic :: Scientific/Engineering
Requires-Python: >=3.6
License-File: LICENSE
Requires-Dist: synonym_dict>=0.2.4
Requires-Dist: pydantic>=2.5.0
Dynamic: license-file
